service_installer/__init__.py
service_installer/__main__.py
service_installer/service_installer.py
template_service_installer-0.1.3.dist-info/METADATA
template_service_installer-0.1.3.dist-info/WHEEL
template_service_installer-0.1.3.dist-info/top_level.txt
template_service_installer-0.1.3.dist-info/RECORD
