Metadata-Version: 2.1
Name: template-service-installer
Version: 0.1.3
Summary: Library for automating the installation of systemd services
Home-page: https://github.com/Fox-sys/service_installer
Author-email: berestovborisasz@gmail.com
